mcumgr_client_wrapper-0.3.0.dist-info/METADATA
mcumgr_client_wrapper-0.3.0.dist-info/WHEEL
mcumgr_client/__init__.py
mcumgr_client/mcumgr_client.cpython-311-arm-linux-gnueabihf.so
mcumgr_client_wrapper-0.3.0.dist-info/RECORD
